{
  "$id": "https://kf-ui-datatracker.kidsfirstdrc.org/event_schemas/CREATE_NEW_DOCUMENT/CREATE_NEW_DOCUMENT__HOVER.schema.json",
  "$schema": "http://json-schema.org/draft-04/schema#",
  "title": "CREATE_NEW_DOCUMENT__HOVER",
  "type": "object",
  "description": "onMouseOver event for the UploadWizard 'Create New Document' button",
  "allOf": [
    {"$ref": "../common_defintions.json#/path"},
    {"$ref": "../common_defintions.json#/route"},
    {"$ref": "../common_defintions.json#/view"},
    {"$ref": "../common_defintions.json#/file"},
    {"$ref": "../BUTTON/button_defintions.json#/button_text"},
    {
      "properties": {
        "study": {
          "type": "object",
          "allOf": [
            {"$ref": "../common_defintions.json#/study"},
            {
              "properties": {
                "name": {"type": "string", "description": "study long name"},
                "documents": {
                  "type": "number",
                  "description": "length of documents in study"
                }
              }
            }
          ]
        },
        "similar_documents": {
          "type": "array",
          "properties": {
            "name": {
              "type": "string",
              "decription": "name of the local file"
            },
            "rating": {
              "type": "number",
              "description": "floating point representing the string similarity (Dice's Coefficient) between the file name of the local file to the document name of an existing document",
              "examples": [0.04878048780487805]
            },
            "kfId": {
              "type": "string",
              "description": "kids first study file identifier",
              "examples": ["SF_7F2EW7WS"],
              "pattern": "^SF_[A-HJ-KM-NP-TV-Z0-9]{8}"
            }
          }
        },
        "step_title": {
          "type": "string",
          "description": "title of the current step in the multi-step process"
        }
      }
    }
  ]
}
